cmem_plugin_python/__init__.py
cmem_plugin_python/package_management.py
cmem_plugin_python/python_icon.svg
cmem_plugin_python/test_transform_operator.py
cmem_plugin_python/workflow_task.py
cmem_plugin_python-1.2.1.dist-info/METADATA
cmem_plugin_python-1.2.1.dist-info/WHEEL
cmem_plugin_python-1.2.1.dist-info/licenses/LICENSE
cmem_plugin_python-1.2.1.dist-info/RECORD
