Metadata-Version: 2.4
Name: cmem-plugin-python
Version: 1.2.1
Summary: Write ad-hoc transformations and workflow tasks with Python.
License: Apache-2.0
License-File: LICENSE
Keywords: eccenca Corporate Memory,plugin
Author: eccenca GmbH
Author-email: cmempy-developer@eccenca.com
Requires-Python: >=3.11,<4.0
Classifier: Development Status :: 4 - Beta
Classifier: Environment :: Plugins
Classifier: License :: OSI Approved :: Apache Software License
Classifier: Programming Language :: Python :: 3
Classifier: Programming Language :: Python :: 3.11
Classifier: Programming Language :: Python :: 3.12
Classifier: Programming Language :: Python :: 3.13
Classifier: Programming Language :: Python :: 3.14
Requires-Dist: cmem-plugin-base (>=4.12.1,<5.0.0)
Requires-Dist: cmem_cmempy (>=25.3.0,<26.0.0)
Requires-Dist: pydantic (>=2.11.4,<3.0.0)
Project-URL: Homepage, https://github.com/eccenca/cmem-plugin-python
